Workbook

Sheet Model
B1: 2016 | C1: =B1+1 -> 2017 | D1: =C1+1 -> 2018 | E1: =D1+1 -> 2019 | F1: =E1+1 -> 2020 | G1: =F1+1 -> 2021 | H1: =G1+1 -> 2022 | I1: =H1+1 -> 2023 | J1: =I1+1 -> 2024 | ... P1: =O1+1 -> 2030
A2: Revenue
A3: Gross Revenue from operations | B3: 30700.88 | C3: 30958.19 | D3: 33100.94 | E3: 33972.23 | F3: 28836.09 | G3: 30959.19 | H3: 29245.47 | I3: 33805.65 | J3: 37455.72 | K3: =(K98*K119)/(10^6) -> 50593.039 | L3: =(L98*L119)/(10^6) -> 60930.328 | M3: =(M98*M119)/(10^6) -> 73387.317 | N3: =(N98*N119)/(10^6) -> 88400.027 | O3: =(O98*O119)/(10^6) -> 106494.41 | P3: =(P98*P119)/(10^6) -> 128304.94
A4: Other Income | B4: 422.43 | C4: 521.95 | D4: 523.17 | E4: 691.25 | F4: 778.34 | G4: 557.9 | H4: 556.91 | I4: 565.16 | J4: 892.55 | K4: =J4+(J4*2%) -> 910.401 | L4: =K4+(K4*2%) -> 928.60902 | M4: =L4+(L4*2%) -> 947.1812 | N4: =M4+(M4*2%) -> 966.12482 | O4: =N4+(N4*2%) -> 985.44732 | P4: =O4+(O4*2%) -> 1005.1563
A6: Total Revenue | B6: =SUM(B3:B4) -> 31123.31 | C6: =SUM(C3:C4) -> 31480.14 | D6: =SUM(D3:D4) -> 33624.11 | E6: =SUM(E3:E4) -> 34663.48 | F6: =SUM(F3:F4) -> 29614.43 | G6: =SUM(G3:G4) -> 31517.09 | H6: =SUM(H3:H4) -> 29802.38 | I6: =SUM(I3:I4) -> 34370.81 | ... P6: =SUM(P3:P4) -> 129310.1
A8: Costs
A9: Raw Materials | B9: 19321.72 | C9: 18993.87 | D9: 21995.94 | E9: 23346.1 | F9: 19867.19 | G9: 21968.04 | H9: 20708.07 | I9: 24019.73 | J9: 24767.46 | K9: =$K$3*K124 -> 34123.554 | L9: =$L$3*L124 -> 41917.674 | M9: =$M$3*M124 -> 51497.346 | N9: =$N$3*N124 -> 63272.705 | O9: =$O$3*O124 -> 77748.315 | P9: =$P$3*P124 -> 95544.949
A10: Purchases | B10: 0 | C10: 0 | D10: 0 | E10: 0 | F10: 0 | G10: 31.14 | H10: 45.95 | I10: 47.43 | J10: 484.2 | K10: =$K$3*K125 -> 667.11019 | L10: =$L$3*L125 -> 819.48403 | M10: =$M$3*M125 -> 1006.7651 | N10: =$N$3*N125 -> 1236.9716 | O10: =$O$3*O125 -> 1519.9675 | P10: =$P$3*P125 -> 1867.8889
A11: Changes in Stock in Trade | B11: -11.88 | C11: 96.74 | D11: -110.12 | E11: -28.38 | F11: -169.78 | G11: -255.57 | H11: 72.71 | I11: -209.04 | J11: 179.11 | K11: =$K$3*K126 -> 246.77015 | L11: =$L$3*L126 -> 303.13462 | M11: =$M$3*M126 -> 372.41161 | N11: =$N$3*N126 -> 457.56708 | O11: =$O$3*O126 -> 562.24985 | P11: =$P$3*P126 -> 690.94917
A12: Employee Cost | B12: 1315.93 | C12: 1432.49 | D12: 1583.71 | E12: 1730.24 | F12: 1841.7 | G12: 1951.02 | H12: 1935.44 | I12: 2189.83 | J12: 2402.34 | K12: =$K$3*K127 -> 3309.842 | L12: =$L$3*L127 -> 4065.839 | M12: =$M$3*M127 -> 4995.0271 | N12: =$N$3*N127 -> 6137.1877 | O12: =$O$3*O127 -> 7541.2612 | P12: =$P$3*P127 -> 9267.4603
A13: Other Expenses | B13: 3361.96 | C13: 3485.89 | D13: 3663.79 | E13: 3672.49 | F13: 3339.02 | G13: 3165.05 | H13: 3114.53 | I13: 3771.47 | J13: 4366.9 | K13: =$K$3*K128 -> 6016.5293 | L13: =$L$3*L128 -> 7390.7575 | M13: =$M$3*M128 -> 9079.8071 | N13: =$N$3*N128 -> 11155.992 | O13: =$O$3*O128 -> 13708.273 | P13: =$P$3*P128 -> 16846.105
A14: Excise Duty | B14: 2258.18 | C14: 2371.13 | D14: 642.57 | E14: 1.41 | F14: 1.35 | G14: 2.91 | H14: 13.16 | I14: 9.43 | J14: 3.19 | K14: =$K$3*K129 -> 4.3950465 | L14: =$L$3*L129 -> 5.3989138 | M14: =$M$3*M129 -> 6.6327566 | N14: =$N$3*N129 -> 8.1493997 | O14: =$O$3*O129 -> 10.01383 | P14: =$P$3*P129 -> 12.306001
A16: Total Costs | B16: =SUM(B9:B14) -> 26245.91 | C16: =SUM(C9:C14) -> 26380.12 | D16: =SUM(D9:D14) -> 27775.89 | E16: =SUM(E9:E14) -> 28721.86 | F16: =SUM(F9:F14) -> 24879.48 | G16: =SUM(G9:G14) -> 26862.59 | H16: =SUM(H9:H14) -> 25889.86 | I16: =SUM(I9:I14) -> 29828.85 | ... P16: =SUM(P9:P14) -> 124229.66
A18: Operating Profits | B18: =B6-B16 -> 4877.4 | C18: =C6-C16 -> 5100.02 | D18: =D6-D16 -> 5848.22 | E18: =E6-E16 -> 5941.62 | F18: =F6-F16 -> 4734.95 | G18: =G6-G16 -> 4654.5 | H18: =H6-H16 -> 3912.52 | I18: =I6-I16 -> 4541.96 | ... P18: =P6-P16 -> 5080.4388
A20: Depreciation & Amortization | B20: 437.64 | C20: 492.73 | D20: 574.98 | E20: 624.44 | F20: 845.76 | G20: 715.12 | H20: 689.52 | I20: 697.39 | J20: 711.41 | K20: =K204 -> 862.99014 | L20: =L204 -> 895.40809 | M20: =M204 -> 931.06783 | N20: =N204 -> 970.29354 | O20: =O204 -> 1013.4418 | P20: =P204 -> 1060.9049
A22: EBIT | B22: =B18-B20 -> 4439.76 | C22: =C18-C20 -> 4607.29 | D22: =D18-D20 -> 5273.24 | E22: =E18-E20 -> 5317.18 | F22: =F18-F20 -> 3889.19 | G22: =G18-G20 -> 3939.38 | H22: =H18-H20 -> 3223 | I22: =I18-I20 -> 3844.57 | ... P22: =P18-P20 -> 4019.5338
A24: Interest | B24: 4.89 | C24: 6.05 | D24: 6.25 | E24: 8.6 | F24: 22.02 | G24: 21.84 | H24: 25.8 | I24: 19.87 | J24: 18.5 | K24: 20 | L24: 20 | M24: 20 | N24: 20 | O24: 20 | P24: 20
A26: Profit Before Exceptional Items and Taxes | B26: =B22-B24 -> 4434.87 | C26: =C22-C24 -> 4601.24 | D26: =D22-D24 -> 5266.99 | E26: =E22-E24 -> 5308.58 | F26: =F22-F24 -> 3867.17 | G26: =G22-G24 -> 3917.54 | H26: =H22-H24 -> 3197.2 | I26: =I22-I24 -> 3824.7 | ... P26: =P22-P24 -> 3999.5338
A27: Other/Exceptional Items | B27: 0 | C27: ='Notes and Assumptions'!D3 -> 50 | D27: ='Notes and Assumptions'!E3 -> 55 | E27: ='Notes and Assumptions'!F3 -> 60.5 | F27: ='Notes and Assumptions'!G3 -> 66.55 | G27: ='Notes and Assumptions'!H3 -> 73.205 | H27: ='Notes and Assumptions'!I3 -> 80.5255 | I27: ='Notes and Assumptions'!J3 -> 88.57805 | J27: -160 | K27: 80 | L27: 80 | M27: 80 | N27: 80 | O27: 80 | P27: 80
A28: Profit Before Taxes | B28: =SUM(B26:B27) -> 4434.87 | C28: =SUM(C26:C27) -> 4651.24 | D28: =SUM(D26:D27) -> 5321.99 | E28: =SUM(E26:E27) -> 5369.08 | F28: =SUM(F26:F27) -> 3933.72 | G28: =SUM(G26:G27) -> 3990.745 | H28: =SUM(H26:H27) -> 3277.7255 | I28: =SUM(I26:I27) -> 3913.2781 | ... P28: =SUM(P26:P27) -> 4079.5338
A30: Taxes | B30: 1274.68 | C30: 1281.34 | D30: 1546.8 | E30: 1625.86 | F30: 940.43 | G30: 913.27 | H30: 729.06 | I30: 963.98 | J30: 1290.4 | K30: =K28*K31 -> 1899.6747 | L30: =L28*L31 -> 1956.3721 | M30: =M28*M31 -> 1951.6323 | N30: =N28*N31 -> 1856.1856 | O30: =O28*O31 -> 1630.8999 | P30: =P28*P31 -> 1223.8602
A31: Tax Rate | K31: 0.3 | L31: 0.3 | M31: 0.3 | N31: 0.3 | O31: 0.3 | P31: 0.3
A32: Profit Before Minority Interest and Share in Associates | B32: =B28-B30 -> 3160.19 | C32: =C28-C30 -> 3369.9 | D32: =D28-D30 -> 3775.19 | E32: =E28-E30 -> 3743.22 | F32: =F28-F30 -> 2993.29 | G32: =G28-G30 -> 3077.475 | H32: =H28-H30 -> 2548.6655 | I32: =I28-I30 -> 2949.2981 | ... P32: =P28-P30 -> 2855.6737
A36: Profit for the Year | B36: =B32+B33 -> 3160.19 | C36: =C32+C33 -> 3369.9 | D36: =D32+D33 -> 3775.19 | E36: =E32+E33 -> 3743.22 | F36: =F32+F33 -> 2993.29 | G36: =G32+G33 -> 3077.475 | H36: =H32+H33 -> 2548.6655 | I36: =I32+I33 -> 2949.2981 | ... P36: =P32+P33 -> 2855.6737
A39: Sources of Funds
A41: Shareholder Funds
A42: Share Capital | B42: 39.94 | C42: 39.94 | D42: 39.94 | E42: 39.94 | F42: 39.95 | G42: 39.96 | H42: 39.96 | I42: 39.97 | J42: 39.98 | K42: 39.98 | L42: 39.98 | M42: 39.98 | N42: 39.98 | O42: 39.98 | P42: 39.98
A43: Reserves & Surplus | B43: 8794.47 | C43: 10071.35 | D43: 11728.94 | E43: 12817.17 | F43: 14096.45 | G43: 15158 | H43: 15806.69 | I43: 16665.12 | J43: 17946.2 | K43: =J43*102% -> 18305.124 | L43: =K43*102% -> 18671.226 | M43: =L43*102% -> 19044.651 | N43: =M43*102% -> 19425.544 | O43: =N43*102% -> 19814.055 | P43: =O43*102% -> 20210.336
A44: Total Equity | B44: =SUM(B42:B43) -> 8834.41 | C44: =SUM(C42:C43) -> 10111.29 | D44: =SUM(D42:D43) -> 11768.88 | E44: =SUM(E42:E43) -> 12857.11 | F44: =SUM(F42:F43) -> 14136.4 | G44: =SUM(G42:G43) -> 15197.96 | H44: =SUM(H42:H43) -> 15846.65 | I44: =SUM(I42:I43) -> 16705.09 | ... P44: =SUM(P42:P43) -> 20250.316
A49: Long Term Liabilities | B49: =SUM(B50:B53) -> 290.13 | C49: =SUM(C50:C53) -> 489.64 | D49: =SUM(D50:D53) -> 626.6 | E49: =SUM(E50:E53) -> 653.71 | F49: =SUM(F50:F53) -> 636.87 | G49: =SUM(G50:G53) -> 852.4 | H49: =SUM(H50:H53) -> 798.43 | I49: =SUM(I50:I53) -> 934.07 | ... P49: =SUM(P50:P53) -> 1231.0705
A50: Lease/Loans | B50: 0 | C50: 0 | D50: 0 | E50: 0 | F50: 121.67 | G50: 129.81 | H50: 142.32 | I50: 134.29 | J50: 111.5 | K50: =J50*102% -> 113.73 | L50: =K50*103% -> 117.1419 | M50: =L50*103% -> 120.65616 | N50: =M50*103% -> 124.27584 | O50: =N50*103% -> 128.00412 | P50: =O50*103% -> 131.84424
A51: Other Long Term Liabilities | B51: 0 | C51: 0 | D51: 0 | E51: 0 | F51: 0 | G51: 146.04 | H51: 155.04 | I51: 196.29 | J51: 178.13 | K51: =J51*102% -> 181.6926 | L51: =K51*103% -> 187.14338 | M51: =L51*103% -> 192.75768 | N51: =M51*103% -> 198.54041 | O51: =N51*103% -> 204.49662 | P51: =O51*103% -> 210.63152
A52: Long Term Provisions | B52: 67.6 | C52: 75.3 | D52: 114.94 | E52: 117.2 | F52: 122.37 | G52: 172.46 | H52: 178.07 | I52: 198.12 | J52: 316.66 | K52: =J52*102% -> 322.9932 | L52: =K52*103% -> 332.683 | M52: =L52*103% -> 342.66349 | N52: =M52*103% -> 352.94339 | O52: =N52*103% -> 363.53169 | P52: =O52*103% -> 374.43764
A53: Deferred Tax Liabilities | B53: 222.53 | C53: 414.34 | D53: 511.66 | E53: 536.51 | F53: 392.83 | G53: 404.09 | H53: 323 | I53: 405.37 | J53: 434.82 | K53: =J53*102% -> 443.5164 | L53: =K53*103% -> 456.82189 | M53: =L53*103% -> 470.52655 | N53: =M53*103% -> 484.64235 | O53: =N53*103% -> 499.18162 | P53: =O53*103% -> 514.15706
A55: Current Liabilities | B55: =SUM(B57:B61) -> 3448.32 | C55: =SUM(C57:C61) -> 4093.33 | D55: =SUM(D57:D61) -> 4343.32 | E55: =SUM(E57:E61) -> 4130.36 | F55: =SUM(F57:F61) -> 3976.06 | G55: =SUM(G57:G61) -> 6110.22 | H55: =SUM(H57:H61) -> 5072.38 | I55: =SUM(I57:I61) -> 5623.98 | ... P55: =SUM(P57:P61) -> 21683.535
A57: Short Term Borrowings | B57: 0 | C57: 0 | D57: 0 | E57: 0 | F57: 28.29 | G57: 19.7 | H57: 25.75 | I57: 22.02 | J57: 26.08 | K57: =K163 -> 556.52343 | L57: =L163 -> 670.2336 | M57: =M163 -> 807.26049 | N57: =N163 -> 972.40029 | O57: =O163 -> 1171.4385 | P57: =P163 -> 1411.3544
A58: Trade Payables | B58: 2650.56 | C58: 3247.27 | D58: 3318.81 | E58: 3355.28 | F58: =8.33+3022.18 -> 3030.51 | G58: =15.71+5188.9 -> 5204.61 | H58: =25.55+4234.79 -> 4260.34 | I58: =1.15+4703.31 -> 4704.46 | J58: =15.79+5512.36 -> 5528.15 | K58: =K164 -> 6071.1647 | L58: =L164 -> 7311.6393 | M58: =M164 -> 8806.4781 | N58: =N164 -> 10608.003 | O58: =O164 -> 12779.329 | P58: =P164 -> 15396.593
A59: Other Current Liabilities | B59: 502.4 | C59: 454.28 | D59: 762.58 | E59: 495.18 | F59: 518.26 | G59: 566.01 | H59: 492.12 | I59: 557.84 | J59: 585.6 | K59: =K165 -> 758.89559 | L59: =L165 -> 913.95491 | M59: =M165 -> 1100.8098 | N59: =N165 -> 1326.0004 | O59: =O165 -> 1597.4161 | P59: =P165 -> 1924.5741
A60: Short Term Provisions | B60: 29.66 | C60: 39.01 | D60: 59.79 | E60: 59.03 | F60: 146.56 | G60: 160.37 | H60: 160.42 | I60: 175.69 | J60: 154.14 | K60: =K166 -> 505.93039 | L60: =L166 -> 609.30328 | M60: =M166 -> 733.87317 | N60: =N166 -> 884.00027 | O60: =O166 -> 1064.9441 | P60: =P166 -> 1283.0494
A61: Other Finance Liabilities | B61: 265.7 | C61: 352.77 | D61: 202.14 | E61: 220.87 | F61: 252.44 | G61: 159.53 | H61: 133.75 | I61: 163.97 | J61: 250.29 | K61: =K167 -> 657.70951 | L61: =L167 -> 792.09426 | M61: =M167 -> 954.03512 | N61: =N167 -> 1149.2003 | O61: =O167 -> 1384.4273 | P61: =P167 -> 1667.9642
A62: Total | B62: =SUM(B44,B49,B55) -> 12572.86 | C62: =SUM(C44,C49,C55) -> 14694.26 | D62: =SUM(D44,D49,D55) -> 16738.8 | E62: =SUM(E44,E49,E55) -> 17641.18 | F62: =SUM(F44,F49,F55) -> 18749.33 | G62: =SUM(G44,G49,G55) -> 22160.58 | H62: =SUM(H44,H49,H55) -> 21717.46 | I62: =SUM(I44,I49,I55) -> 23263.14 | ... P62: =SUM(P44,P49,P55) -> 43164.922
A65: Application Of Funds
A67: Long Term Assets | B67: =SUM(B68:B78) -> 6421.64 | C67: =SUM(C68:C78) -> 7241.08 | D67: =SUM(D68:D78) -> 7890.62 | E67: =SUM(E68:E78) -> 9525.55 | F67: =SUM(F68:F78) -> 10460.77 | G67: =SUM(G68:G78) -> 11208.26 | H67: =SUM(H68:H78) -> 11599.06 | I67: =SUM(I68:I78) -> 14226.35 | ... P67: =SUM(P68:P78) -> 5835.9472
A68: Tangible Assets | B68: 3465.46 | C68: 4310.73 | D68: 4485.89 | E68: 4477.53 | F68: 5562.42 | G68: 5293.4 | H68: 5094.39 | I68: 4868.2 | J68: 4933.87 | K68: =J68*90% -> 4440.483 | L68: =K68*90% -> 3996.4347 | M68: =L68*90% -> 3596.7912 | N68: =M68*90% -> 3237.1121 | O68: =N68*90% -> 2913.4009 | P68: =O68*90% -> 2622.0608
A69: Intangible Assets | B69: 118.89 | C69: 84.86 | D69: 168.65 | E69: 141.05 | F69: 140.09 | G69: 290.26 | H69: 298.5 | I69: 500.19 | J69: 528.55 | K69: =J69*90% -> 475.695 | L69: =K69*90% -> 428.1255 | M69: =L69*90% -> 385.31295 | N69: =M69*90% -> 346.78166 | O69: =N69*90% -> 312.10349 | P69: =O69*90% -> 280.89314
A70: Rights of Use Assets | B70: 0 | C70: 0 | D70: 0 | E70: 0 | F70: 414.57 | G70: 404.75 | H70: 413.59 | I70: 393.03 | J70: 371.61 | K70: =J70*90% -> 334.449 | L70: =K70*90% -> 301.0041 | M70: =L70*90% -> 270.90369 | N70: =M70*90% -> 243.81332 | O70: =N70*90% -> 219.43199 | P70: =O70*90% -> 197.48879
A71: Capital Work in Progress | B71: 288.34 | C71: 270.72 | D71: 203.78 | E71: 360.67 | F71: 160.25 | G71: 177.86 | H71: 87.32 | I71: 128.55 | J71: 120.58 | K71: =J71*90% -> 108.522 | L71: =K71*90% -> 97.6698 | M71: =L71*90% -> 87.90282 | N71: =M71*90% -> 79.112538 | O71: =N71*90% -> 71.201284 | P71: =O71*90% -> 64.081156
A72: Intangible Assets Under Development | B72: 317.06 | C72: 194.33 | D72: 114.61 | E72: 181.19 | F72: 181.02 | G72: 258.73 | H72: 370.88 | I72: 335.24 | J72: 359.93 | K72: =J72*90% -> 323.937 | L72: =K72*90% -> 291.5433 | M72: =L72*90% -> 262.38897 | N72: =M72*90% -> 236.15007 | O72: =N72*90% -> 212.53507 | P72: =O72*90% -> 191.28156
A74: Non-Current Investments | B74: 1111.91 | C74: 1349 | D74: 1934.08 | E74: 2801.51 | F74: 3528.17 | G74: 4308.18 | H74: 4814.66 | I74: 7372.48 | J74: 8811.58 | K74: =J74*80% -> 7049.264 | L74: =K74*80% -> 5639.4112 | M74: =L74*80% -> 4511.529 | N74: =M74*80% -> 3609.2232 | O74: =N74*80% -> 2887.3785 | P74: =O74*80% -> 2309.9028
A75: Other Financial Assets | B75: 23.2 | C75: 0 | D75: 0 | E75: 0 | F75: 0 | G75: 35.5 | H75: 41.6 | I75: 205.65 | J75: 188.87 | K75: =J75*80% -> 151.096 | L75: =K75*80% -> 120.8768 | M75: =L75*80% -> 96.70144 | N75: =M75*80% -> 77.361152 | O75: =N75*80% -> 61.888922 | P75: =O75*80% -> 49.511137
A76: Long Term Loans and Advances | B76: 26.7 | C76: 48.36 | D76: 45.68 | E76: 59.96 | F76: 67.27 | G76: 16.73 | H76: 17.43 | I76: 19.87 | J76: 21.15 | K76: =J76*80% -> 16.92 | L76: =K76*80% -> 13.536 | M76: =L76*80% -> 10.8288 | N76: =M76*80% -> 8.66304 | O76: =N76*80% -> 6.930432 | P76: =O76*80% -> 5.5443456
A77: Other Non Current Assets | B77: 842.54 | C77: 651.14 | D77: 558.67 | E77: 664.38 | F77: 96.85 | G77: 54.66 | H77: 119.77 | I77: 151.42 | J77: 126.9 | K77: =J77*80% -> 101.52 | L77: =K77*80% -> 81.216 | M77: =L77*80% -> 64.9728 | N77: =M77*80% -> 51.97824 | O77: =N77*80% -> 41.582592 | P77: =O77*80% -> 33.266074
A78: Income Tax Assets | B78: 227.54 | C78: 331.94 | D78: 379.26 | E78: 839.26 | F78: 310.13 | G78: 368.19 | H78: 340.92 | I78: 251.72 | J78: 312.49 | K78: =J78*80% -> 249.992 | L78: =K78*80% -> 199.9936 | M78: =L78*80% -> 159.99488 | N78: =M78*80% -> 127.9959 | O78: =N78*80% -> 102.39672 | P78: =O78*80% -> 81.917379
A80: Current Assets | B80: =SUM(B82:B89) -> 6151.22 | C80: =SUM(C82:C89) -> 7453.18 | D80: =SUM(D82:D89) -> 8848.18 | E80: =SUM(E82:E89) -> 8115.57 | F80: =SUM(F82:F89) -> 8288.56 | G80: =SUM(G82:G89) -> 10952.79 | H80: =SUM(H82:H89) -> 10117.96 | I80: =SUM(I82:I89) -> 9036.79 | ... P80: =SUM(P82:P89) -> 37328.641
A82: Inventories | B82: 672.98 | C82: 656.31 | D82: 823.58 | E82: 1072.3 | F82: 1091.97 | G82: 1469.55 | H82: 1122.65 | I82: 1434.09 | J82: 1443.76 | K82: =Model!K154 -> 2529.652 | L82: =Model!L154-445 -> 2601.5164 | M82: =Model!M154-68 -> 3601.3659 | N82: =Model!N154 -> 4420.0013 | O82: =Model!O154 -> 5324.7204 | P82: =Model!P154 -> 6415.2471
A83: Receivables | B83: 1282.8 | C83: 1561.87 | D83: 1520.18 | E83: 2821.57 | F83: 1603.14 | G83: 2426.76 | H83: 2304.27 | I83: 2798.21 | J83: 2703.44 | K83: =Model!K155 -> 3794.478 | L83: =Model!L155 -> 4569.7746 | M83: =Model!M155 -> 5504.0488 | N83: =Model!N155 -> 6630.002 | O83: =Model!O155 -> 7987.0806 | P83: =Model!P155 -> 9622.8706
A84: Cash & Bank Balances | B84: =26.95+104.41 -> 131.36 | C84: =15.4+121.33 -> 136.73 | D84: =34.38+106.96 -> 141.34 | E84: =40.68+95.78 -> 136.46 | F84: =147.91+93.95 -> 241.86 | G84: =169.22+ 87.93 -> 257.15 | H84: =98.68+76.44 -> 175.12 | I84: =168.37+177.13 -> 345.5 | J84: =539.89+69.04 -> 608.93 | K84: =J84*105% -> 639.3765 | L84: =K84*105% -> 671.34533 | M84: =L84*105% -> 704.91259 | N84: =M84*105% -> 740.15822 | O84: =N84*105% -> 777.16613 | P84: =O84*105% -> 816.02444
A85: Loans & Advances | B85: 23.12 | C85: 24.18 | D85: 27.56 | E85: 25.03 | F85: 22.36 | G85: 22.95 | H85: 22.81 | I85: 23.71 | J85: 24.56 | K85: =K156 -> 505.93039 | L85: =L156 -> 609.30328 | M85: =M156 -> 733.87317 | N85: =N156 -> 884.00027 | O85: =O156 -> 1064.9441 | P85: =P156 -> 1283.0494
A86: Other Current Assets | B86: 549.57 | C86: 388.29 | D86: 205.03 | E86: 239.22 | F86: 280.14 | G86: 213.37 | H86: 197.65 | I86: 235.07 | J86: 457.3 | K86: =K157 -> 607.11647 | L86: =L157 -> 731.16393 | M86: =M157 -> 880.64781 | N86: =N157 -> 1060.8003 | O86: =O157 -> 1277.9329 | P86: =P157 -> 1539.6593
A87: Current Tax Asset | B87: 0 | C87: 0 | D87: 0 | E87: 0 | F87: 0 | G87: 0 | H87: 0 | I87: 0 | J87: 0 | K87: =K158 -> 505.93039 | L87: =L158 -> 609.30328 | M87: =M158 -> 733.87317 | N87: =N158 -> 884.00027 | O87: =O158 -> 1064.9441 | P87: =P158 -> 1283.0494
A88: Investments | B88: 3469.11 | C88: 4540.85 | D88: 5591.12 | E88: 3167.1 | F88: 4694.48 | G88: 6191.49 | H88: 5840.66 | I88: 3637.88 | J88: 4274.52 | K88: -1466 | L88: 0 | M88: 0 | N88: -332 | O88: -1253 | P88: -2877
A89: Other Financial Assets | B89: 22.28 | C89: 144.95 | D89: 539.37 | E89: 653.89 | F89: 354.61 | G89: 371.52 | H89: 454.8 | I89: 562.33 | J89: 283.51 | K89: =K159 -> 7588.9559 | L89: =L159 -> 9139.5491 | M89: =M159 -> 11008.098 | N89: =N159 -> 13260.004 | O89: =O159 -> 15974.161 | P89: =P159 -> 19245.741
A90: Total | B90: =SUM(B80,B67) -> 12572.86 | C90: =SUM(C80,C67) -> 14694.26 | D90: =SUM(D80,D67) -> 16738.8 | E90: =SUM(E80,E67) -> 17641.12 | F90: =SUM(F80,F67) -> 18749.33 | G90: =SUM(G80,G67) -> 22161.05 | H90: =SUM(H80,H67) -> 21717.02 | I90: =SUM(I80,I67) -> 23263.14 | ... P90: =SUM(P80,P67) -> 43164.589
A91: check (asset = liabilities) (should be zero) | B91: =B62-B90 -> 0 | C91: =C62-C90 -> 0 | D91: =D62-D90 -> 0 | E91: =E62-E90 -> 0.06 | F91: =F62-F90 -> 0 | G91: =G62-G90 -> -0.47 | H91: =H62-H90 -> 0.44 | I91: =I62-I90 -> 0 | ... P91: =P62-P90 -> 0.33292287
A93: Capacity | B93: 6762980 | C93: 7207363 | D93: 7587130 | E93: 7820745 | F93: 6400000 | G93: 5800000 | H93: 4900000 | I93: 5300000 | J93: 5600000 | K93: =J93+K94 -> 5798000 | L93: =K93+L94 -> 6015800 | M93: =L93+M94 -> 6255380 | N93: =M93+N94 -> 6518918 | O93: =N93+O94 -> 6808809.8 | P93: =O93+P94 -> 7127690.8
A94: New Capacity | C94: =C93-B93 -> 444383 | D94: =D93-C93 -> 379767 | E94: =E93-D93 -> 233615 | F94: =F93-E93 -> -1420745 | G94: =G93-F93 -> -600000 | H94: =H93-G93 -> -900000 | I94: =I96-H93 -> 520000 | J94: =J93-I96 -> 180000 | K94: =J94*110% -> 198000 | L94: =K94*110% -> 217800 | M94: =L94*110% -> 239580 | N94: =M94*110% -> 263538 | O94: =N94*110% -> 289891.8 | P94: =O94*110% -> 318880.98
A96: Domestic | B96: 6486103 | C96: 7207363 | D96: 7360000 | E96: 7612775 | F96: 6231458 | G96: 5039092 | H96: 4900000 | I96: 5420000 | J96: 5550200
A97: Exports | B97: 146800 | C97: 183846 | D97: 194000 | E97: 282000 | F97: 270000 | G97: 238941 | H97: 288788 | I97: 225800 | J97: 186644
A98: Total | B98: =B96+B97 -> 6632903 | C98: =C96+C97 -> 7391209 | D98: =D96+D97 -> 7554000 | E98: =E96+E97 -> 7894775 | F98: =F96+F97 -> 6501458 | G98: =G96+G97 -> 5278033 | H98: =H96+H97 -> 5188788 | I98: =I96+I97 -> 5645800 | J98: =J96+J97 -> 5736844 | K98: =K109*K116 -> 6918750 | L98: =L109*L116 -> 7439647.5 | M98: =M109*M116 -> 8000586.7 | N98: =N109*N116 -> 8604689.4 | O98: =O109*O116 -> 9255323 | P98: =P109*P116 -> 9956120.3
A100: Capacity Utilization | B100: =B98/B93 -> 0.98076632 | C100: =C98/C93 -> 1.0255081 | D100: =D98/D93 -> 0.99563339 | E100: =E98/E93 -> 1.0094659 | F100: =F98/F93 -> 1.0158528 | G100: =G98/G93 -> 0.91000569 | H100: =H98/H93 -> 1.0589363 | I100: =I98/I93 -> 1.0652453 | ... P100: =P98/P93 -> 1.3968227
A102: Growth in Domestic Sales | C102: =C96/B96-1 -> 0.11120082 | D102: =D96/C96-1 -> 0.021177926 | E102: =E96/D96-1 -> 0.034344429 | F102: =F96/E96-1 -> -0.18144724 | G102: =G96/F96-1 -> -0.19134623 | H102: =H96/G96-1 -> -0.027602592 | I102: =I96/H96-1 -> 0.10612245 | J102: =J96/I96-1 -> 0.02402214
A103: Growth in Export Sales | C103: =C97/B97-1 -> 0.25235695 | D103: =D97/C97-1 -> 0.055231009 | E103: =E97/D97-1 -> 0.45360825 | F103: =F97/E97-1 -> -0.042553191 | G103: =G97/F97-1 -> -0.11503333 | H103: =H97/G97-1 -> 0.20861635 | I103: =I97/H97-1 -> -0.21811156 | J103: =J97/I97-1 -> -0.1734101
A104: Growth in Total Sales | C104: =C98/B98-1 -> 0.1143249 | D104: =D98/C98-1 -> 0.022024949 | E104: =E98/D98-1 -> 0.045111861 | F104: =F98/E98-1 -> -0.17648597 | G104: =G98/F98-1 -> -0.18817702 | H104: =H98/G98-1 -> -0.016908761 | I104: =I98/H98-1 -> 0.08807683 | J104: =J98/I98-1 -> 0.01612597
A106: Industry Data
A107: Domestic Sales | B107: 16000000 | C107: 17700000 | D107: 20200000 | E107: 21000000 | F107: 17400000 | G107: 15100000 | H107: 13600000 | I107: 15900000 | J107: 18000000 | K107: =J107*(1+K110) -> 19440000 | L107: =K107*(1+L110) -> 20995200 | M107: =L107*(1+M110) -> 22674816 | N107: =M107*(1+N110) -> 24488801 | O107: =N107*(1+O110) -> 26447905 | P107: =O107*(1+P110) -> 28563738
A108: Exports | B108: 2700000 | C108: 3100000 | D108: 3500000 | E108: 3300000 | F108: 3500000 | G108: 4021000 | H108: 4440000 | I108: 3650000 | J108: 3450000 | K108: =J108*(1+K111) -> 3622500 | L108: =K108*(1+L111) -> 3803625 | M108: =L108*(1+M111) -> 3993806.2 | N108: =M108*(1+N111) -> 4193496.6 | O108: =N108*(1+O111) -> 4403171.4 | P108: =O108*(1+P111) -> 4623330
A109: Total | B109: =B107+B108 -> 18700000 | C109: =C107+C108 -> 20800000 | D109: =D107+D108 -> 23700000 | E109: =E107+E108 -> 24300000 | F109: =F107+F108 -> 20900000 | G109: =G107+G108 -> 19121000 | H109: =H107+H108 -> 18040000 | I109: =I107+I108 -> 19550000 | ... P109: =P107+P108 -> 33187068
A110: Growth in Domestic Market | C110: =C107/B107-1 -> 0.10625 | D110: =D107/C107-1 -> 0.14124294 | E110: =E107/D107-1 -> 0.03960396 | F110: =F107/E107-1 -> -0.17142857 | G110: =G107/F107-1 -> -0.13218391 | H110: =H107/G107-1 -> -0.099337748 | I110: =I107/H107-1 -> 0.16911765 | J110: =J107/I107-1 -> 0.13207547 | K110: 0.08 | L110: 0.08 | M110: 0.08 | N110: 0.08 | O110: 0.08 | P110: 0.08
A111: Growth in Exports | C111: =C108/B108-1 -> 0.14814815 | D111: =D108/C108-1 -> 0.12903226 | E111: =E108/D108-1 -> -0.057142857 | F111: =F108/E108-1 -> 0.060606061 | G111: =G108/F108-1 -> 0.14885714 | H111: =H108/G108-1 -> 0.10420293 | I111: =I108/H108-1 -> -0.17792793 | J111: =J108/I108-1 -> -0.054794521 | K111: 0.05 | L111: 0.05 | M111: 0.05 | N111: 0.05 | O111: 0.05 | P111: 0.05
A113: Market Share
A114: Domestic | B114: =B96/B107 -> 0.40538144 | C114: =C96/C107 -> 0.40719565 | D114: =D96/D107 -> 0.36435644 | E114: =E96/E107 -> 0.3625131 | F114: =F96/F107 -> 0.35812977 | G114: =G96/G107 -> 0.3337147 | H114: =H96/H107 -> 0.36029412 | I114: =I96/I107 -> 0.3408805 | J114: =J96/J107 -> 0.30834444
A115: Exports | B115: =B97/B108 -> 0.05437037 | C115: =C97/C108 -> 0.059305161 | D115: =D97/D108 -> 0.055428571 | E115: =E97/E108 -> 0.085454545 | F115: =F97/F108 -> 0.077142857 | G115: =G97/G108 -> 0.059423278 | H115: =H97/H108 -> 0.065042342 | I115: =I97/I108 -> 0.061863014 | J115: =J97/J108 -> 0.05409971
A116: Overall | B116: =B98/B109 -> 0.3547007 | C116: =C98/C109 -> 0.35534659 | D116: =D98/D109 -> 0.31873418 | E116: =E98/E109 -> 0.32488786 | F116: =F98/F109 -> 0.31107455 | G116: =G98/G109 -> 0.27603331 | H116: =H98/H109 -> 0.28762683 | I116: =I98/I109 -> 0.28878772 | J116: =J98/J109 -> 0.26745193 | K116: 0.3 | L116: 0.3 | M116: 0.3 | N116: 0.3 | O116: 0.3 | P116: 0.3
A119: Revenue Per Car | B119: =(B3/B98)*10^6 -> 4628.5736 | C119: =(C3/C98)*10^6 -> 4188.515 | D119: =(D3/D98)*10^6 -> 4381.9089 | E119: =(E3/E98)*10^6 -> 4303.1283 | F119: =(F3/F98)*10^6 -> 4435.3267 | G119: =(G3/G98)*10^6 -> 5865.6681 | H119: =(H3/H98)*10^6 -> 5636.2815 | I119: =(I3/I98)*10^6 -> 5987.752 | J119: =(J3/J98)*10^6 -> 6528.9766 | K119: =J119+(J119*K120) -> 7312.4537 | L119: =K119+(K119*L120) -> 8189.9482 | M119: =L119+(L119*M120) -> 9172.742 | N119: =M119+(M119*N120) -> 10273.471 | O119: =N119+(N119*O120) -> 11506.288 | P119: =O119+(O119*P120) -> 12887.042
A120: Growth | C120: =C119/B119-1 -> -0.095074346 | D120: =D119/C119-1 -> 0.046172424 | E120: =E119/D119-1 -> -0.0179786 | F120: =F119/E119-1 -> 0.030721446 | G120: =G119/F119-1 -> 0.32248842 | H120: =H119/G119-1 -> -0.039106645 | I120: =I119/H119-1 -> 0.062358564 | J120: =J119/I119-1 -> 0.090388614 | K120: 0.12 | L120: 0.12 | M120: 0.12 | N120: 0.12 | O120: 0.12 | P120: 0.12
A123: Cost Drivers
A124: Raw Materials | B124: =B9/$B$3 -> 0.62935395 | C124: =C9/$C$3 -> 0.61353296 | D124: =D9/$D$3 -> 0.66451104 | E124: =E9/$E$3 -> 0.68721129 | F124: =F9/$F$3 -> 0.68896962 | G124: =G9/$G$3 -> 0.70958058 | H124: =H9/$H$3 -> 0.70807787 | I124: =I9/$I$3 -> 0.71052413 | J124: =J9/$J$3 -> 0.6612464 | K124: =J124+(J124*2%) -> 0.67447133 | L124: =K124+(K124*2%) -> 0.68796075 | M124: =L124+(L124*2%) -> 0.70171997 | N124: =M124+(M124*2%) -> 0.71575437 | O124: =N124+(N124*2%) -> 0.73006946 | P124: =O124+(O124*2%) -> 0.74467085
A125: Purchases | B125: =B10/$B$3 -> 0 | C125: =C10/$B$3 -> 0 | D125: =D10/$D$3 -> 0 | E125: =E10/$E$3 -> 0 | F125: =F10/$F$3 -> 0 | G125: =G10/$G$3 -> 0.0010058403 | H125: =H10/$H$3 -> 0.0015711835 | I125: =I10/$I$3 -> 0.0014030199 | J125: =J10/$J$3 -> 0.012927265 | K125: =J125+(J125*2%) -> 0.01318581 | L125: =K125+(K125*2%) -> 0.013449526 | M125: =L125+(L125*2%) -> 0.013718517 | N125: =M125+(M125*2%) -> 0.013992887 | O125: =N125+(N125*2%) -> 0.014272745 | P125: =O125+(O125*2%) -> 0.014558199
A126: Changes in Stock in Trade | B126: =B11/$B$3 -> -0.00038695959 | C126: =C11/$B$3 -> 0.0031510497 | D126: =D11/$D$3 -> -0.0033267937 | E126: =E11/$E$3 -> -0.0008353882 | F126: =F11/$F$3 -> -0.0058877608 | G126: =G11/$G$3 -> -0.0082550609 | H126: =H11/$H$3 -> 0.002486197 | I126: =I11/$I$3 -> -0.0061835817 | J126: =J11/$J$3 -> 0.0047819131 | K126: =J126+(J126*2%) -> 0.0048775514 | L126: =K126+(K126*2%) -> 0.0049751024 | M126: =L126+(L126*2%) -> 0.0050746045 | N126: =M126+(M126*2%) -> 0.0051760966 | O126: =N126+(N126*2%) -> 0.0052796185 | P126: =O126+(O126*2%) -> 0.0053852109
A127: Employee Cost | B127: =B12/$B$3 -> 0.042862941 | C127: =C12/$B$3 -> 0.046659575 | D127: =D12/$D$3 -> 0.047844865 | E127: =E12/$E$3 -> 0.05093101 | F127: =F12/$F$3 -> 0.063867882 | G127: =G12/$G$3 -> 0.063019091 | H127: =H12/$H$3 -> 0.066179138 | I127: =I12/$I$3 -> 0.064777042 | J127: =J12/$J$3 -> 0.064138134 | K127: =J127+(J127*2%) -> 0.065420897 | L127: =K127+(K127*2%) -> 0.066729315 | M127: =L127+(L127*2%) -> 0.068063901 | N127: =M127+(M127*2%) -> 0.069425179 | O127: =N127+(N127*2%) -> 0.070813683 | P127: =O127+(O127*2%) -> 0.072229957
A128: Other Expenses | B128: =B13/$B$3 -> 0.10950696 | C128: =C13/$B$3 -> 0.11354365 | D128: =D13/$D$3 -> 0.11068538 | E128: =E13/$E$3 -> 0.10810271 | F128: =F13/$F$3 -> 0.11579309 | G128: =G13/$G$3 -> 0.10223297 | H128: =H13/$H$3 -> 0.10649615 | I128: =I13/$I$3 -> 0.1115633 | J128: =J13/$J$3 -> 0.11658833 | K128: =J128+(J128*2%) -> 0.1189201 | L128: =K128+(K128*2%) -> 0.1212985 | M128: =L128+(L128*2%) -> 0.12372447 | N128: =M128+(M128*2%) -> 0.12619896 | O128: =N128+(N128*2%) -> 0.12872294 | P128: =O128+(O128*2%) -> 0.1312974
A129: Vehicles or Dies for Own Usage | B129: =B14/$B$3 -> 0.073554243 | C129: =C14/$B$3 -> 0.077233291 | D129: =D14/$D$3 -> 0.01941244 | E129: =E14/$E$3 -> 4.1504488e-05 | F129: =F14/$F$3 -> 4.6816333e-05 | G129: =G14/$G$3 -> 9.3994707e-05 | H129: =H14/$H$3 -> 0.00044998422 | I129: =I14/$I$3 -> 0.00027894745 | J129: =J14/$J$3 -> 8.5167232e-05 | K129: =J129+(J129*2%) -> 8.6870577e-05 | L129: =K129+(K129*2%) -> 8.8607988e-05 | M129: =L129+(L129*2%) -> 9.0380148e-05 | N129: =M129+(M129*2%) -> 9.2187751e-05 | O129: =N129+(N129*2%) -> 9.4031506e-05 | P129: =O129+(O129*2%) -> 9.5912136e-05
A132: Cost Per Car
A133: Raw Materials | B133: =B9/$B$119 -> 4.1744437 | C133: =C9/$C$119 -> 4.5347503 | D133: =D9/$D$119 -> 5.0197164 | E133: =E9/$E$119 -> 5.4253785 | F133: =F9/$F$119 -> 4.4793071 | G133: =G9/$G$119 -> 3.7451897 | H133: =H9/$H$119 -> 3.6740659 | I133: =I9/$I$119 -> 4.0114771 | J133: =J9/$J$119 -> 3.7934674 | K133: =J133+(J133*2%) -> 3.8693368 | L133: =K133+(K133*2%) -> 3.9467235 | M133: =L133+(L133*2%) -> 4.025658 | N133: =M133+(M133*2%) -> 4.1061712 | O133: =N133+(N133*2%) -> 4.1882946 | P133: =O133+(O133*2%) -> 4.2720605
A134: Purchases | B134: =B10/$B$119 -> 0 | C134: =C10/$C$119 -> 0 | D134: =D10/$D$119 -> 0 | E134: =E10/$E$119 -> 0 | F134: =F10/$F$119 -> 0 | G134: =G10/$G$119 -> 0.0053088581 | H134: =H10/$H$119 -> 0.0081525381 | I134: =I10/$I$119 -> 0.0079211698 | J134: =J10/$J$119 -> 0.0741617 | K134: =J134+(J134*10%) -> 0.08157787 | L134: =K134+(K134*10%) -> 0.089735657 | M134: =L134+(L134*10%) -> 0.098709223 | N134: =M134+(M134*10%) -> 0.10858014 | O134: =N134+(N134*10%) -> 0.11943816 | P134: =O134+(O134*10%) -> 0.13138198
A135: Changes in Stock in Trade | B135: =B11/$B$119 -> -0.0025666654 | C135: =C11/$C$119 -> 0.023096491 | D135: =D11/$D$119 -> -0.0251306 | E135: =E11/$E$119 -> -0.0065952019 | F135: =F11/$F$119 -> -0.038279029 | G135: =G11/$G$119 -> -0.043570484 | H135: =H11/$H$119 -> 0.012900349 | I135: =I11/$I$119 -> -0.034911266 | J135: =J11/$J$119 -> 0.02743309 | K135: =J135+(J135*10%) -> 0.030176399 | L135: =K135+(K135*10%) -> 0.033194039 | M135: =L135+(L135*10%) -> 0.036513442 | N135: =M135+(M135*10%) -> 0.040164787 | O135: =N135+(N135*10%) -> 0.044181265 | P135: =O135+(O135*10%) -> 0.048599392
A136: Employee Cost | B136: =B12/$B$119 -> 0.28430573 | C136: =C12/$C$119 -> 0.34200426 | D136: =D12/$D$119 -> 0.36142011 | E136: =E12/$E$119 -> 0.40208887 | F136: =F12/$F$119 -> 0.41523435 | G136: =G12/$G$119 -> 0.33261684 | H136: =H12/$H$119 -> 0.34338952 | I136: =I12/$I$119 -> 0.36571822 | J136: =J12/$J$119 -> 0.36795047 | K136: =J136+(J136*10%) -> 0.40474552 | L136: =K136+(K136*10%) -> 0.44522007 | M136: =L136+(L136*10%) -> 0.48974208 | N136: =M136+(M136*10%) -> 0.53871628 | O136: =N136+(N136*10%) -> 0.59258791 | P136: =O136+(O136*10%) -> 0.6518467
A137: Other Expenses | B137: =B13/$B$119 -> 0.72634904 | C137: =C13/$C$119 -> 0.83224961 | D137: =D13/$D$119 -> 0.83611733 | E137: =E13/$E$119 -> 0.85344654 | F137: =F13/$F$119 -> 0.75282392 | G137: =G13/$G$119 -> 0.539589 | H137: =H13/$H$119 -> 0.55258595 | I137: =I13/$I$119 -> 0.6298641 | J137: =J13/$J$119 -> 0.66884909 | K137: =J137+(J137*10%) -> 0.73573399 | L137: =K137+(K137*10%) -> 0.80930739 | M137: =L137+(L137*10%) -> 0.89023813 | N137: =M137+(M137*10%) -> 0.97926195 | O137: =N137+(N137*10%) -> 1.0771881 | P137: =O137+(O137*10%) -> 1.184907
A138: Own Use Vehicles | B138: =B14/$B$119 -> 0.48787816 | C138: =C14/$C$119 -> 0.56610278 | D138: =D14/$D$119 -> 0.14664157 | E138: =E14/$E$119 -> 0.00032766859 | F138: =F14/$F$119 -> 0.00030437442 | G138: =G14/$G$119 -> 0.00049610717 | H138: =H14/$H$119 -> 0.0023348727 | I138: =I14/$I$119 -> 0.0015748815 | J138: =J14/$J$119 -> 0.00048859112 | K138: =J138+(J138*10%) -> 0.00053745024 | L138: =K138+(K138*10%) -> 0.00059119526 | M138: =L138+(L138*10%) -> 0.00065031479 | N138: =M138+(M138*10%) -> 0.00071534627 | O138: =N138+(N138*10%) -> 0.00078688089 | P138: =O138+(O138*10%) -> 0.00086556898
A141: Growth
...

Sheet Notes and Assumptions
B1: Assumptions | C1: 2016 | D1: 2017 | E1: 2018 | F1: 2019 | G1: 2020 | H1: 2021 | I1: 2022 | J1: 2023 | K1: 2024
B3: =Model!A27 -> Other/Exceptional Items | C3: 0 | D3: 50 | E3: =D3+(D3*10%) -> 55 | F3: =E3+(E3*10%) -> 60.5 | G3: =F3+(F3*10%) -> 66.55 | H3: =G3+(G3*10%) -> 73.205 | I3: =H3+(H3*10%) -> 80.5255 | J3: =I3+(I3*10%) -> 88.57805
B5: Assumptions | C5: 2025 | D5: 2026 | E5: 2027 | F5: 2028 | G5: 2029 | H5: 2030
B6: New capacity increased by 10% | C6: =Model!K94 -> 198000 | D6: =Model!L94 -> 217800 | E6: =Model!M94 -> 239580 | F6: =Model!N94 -> 263538 | G6: =Model!O94 -> 289891.8 | H6: =Model!P94 -> 318880.98
B7: Assets per Car Capacity increased by 10% | C7: =Model!K198 -> 1240.3561 | D7: =Model!L198 -> 1240.3561 | E7: =Model!M198 -> 1240.3561 | F7: =Model!N198 -> 1240.3561 | G7: =Model!O198 -> 1240.3561 | H7: =Model!P198 -> 1240.3561
B8: Growth in domestic market | C8: 0.08 | D8: 0.08 | E8: 0.08 | F8: 0.08 | G8: 0.08 | H8: 0.08
B9: Growth in Exports | C9: 0.05 | D9: 0.05 | E9: 0.05 | F9: 0.05 | G9: 0.05 | H9: 0.05
B10: Overall market share | C10: =Model!K116 -> 0.3 | D10: =Model!L116 -> 0.3 | E10: =Model!M116 -> 0.3 | F10: =Model!N116 -> 0.3 | G10: =Model!O116 -> 0.3 | H10: =Model!P116 -> 0.3
B11: Market share growth | C11: =Model!K120 -> 0.12 | D11: =Model!L120 -> 0.12 | E11: =Model!M120 -> 0.12 | F11: =Model!N120 -> 0.12 | G11: =Model!O120 -> 0.12 | H11: =Model!P120 -> 0.12
B12: Raw Materials | C12: 0.67447133 | D12: 0.68796075 | E12: 0.70171997 | F12: 0.71575437 | G12: 0.73006946 | H12: 0.74467085
B13: Purchases | C13: 0.01318581 | D13: 0.013449526 | E13: 0.013718517 | F13: 0.013992887 | G13: 0.014272745 | H13: 0.014558199
B14: Changes in Stock in Trade | C14: 0.0048775514 | D14: 0.0049751024 | E14: 0.0050746045 | F14: 0.0051760966 | G14: 0.0052796185 | H14: 0.0053852109
B15: Employee Cost | C15: 0.065420897 | D15: 0.066729315 | E15: 0.068063901 | F15: 0.069425179 | G15: 0.070813683 | H15: 0.072229957
B16: Other Expenses | C16: 0.1189201 | D16: 0.1212985 | E16: 0.12372447 | F16: 0.12619896 | G16: 0.12872294 | H16: 0.1312974
B17: Vehicles or Dies for Own Usage | C17: 8.6870577e-05 | D17: 8.8607988e-05 | E17: 9.0380148e-05 | F17: 9.2187751e-05 | G17: 9.4031506e-05 | H17: 9.5912136e-05
B18: Other income increased by 2% | C18: =Model!K4 -> 910.401 | D18: =Model!L4 -> 928.60902 | E18: =Model!M4 -> 947.1812 | F18: =Model!N4 -> 966.12482 | G18: =Model!O4 -> 985.44732 | H18: =Model!P4 -> 1005.1563
B19: Depreciation as % of LY Net Fixed Assets | C19: =Model!K205 -> 0.12 | D19: =Model!L205 -> 0.12 | E19: =Model!M205 -> 0.12 | F19: =Model!N205 -> 0.12 | G19: =Model!O205 -> 0.12 | H19: =Model!P205 -> 0.12
B20: Interest | C20: =Model!K24 -> 20 | D20: =Model!L24 -> 20 | E20: =Model!M24 -> 20 | F20: =Model!N24 -> 20 | G20: =Model!O24 -> 20 | H20: =Model!P24 -> 20
B21: Other/Exceptional Items | C21: =Model!K27 -> 80 | D21: =Model!L27 -> 80 | E21: =Model!M27 -> 80 | F21: =Model!N27 -> 80 | G21: =Model!O27 -> 80 | H21: =Model!P27 -> 80
B22: Tax Rate | C22: 0.3 | D22: 0.3 | E22: 0.3 | F22: 0.3 | G22: 0.3 | H22: 0.3
B23: Reserves & Surplus increased by 2% | C23: =Model!K43 -> 18305.124 | D23: =Model!L43 -> 18671.226 | E23: =Model!M43 -> 19044.651 | F23: =Model!N43 -> 19425.544 | G23: =Model!O43 -> 19814.055 | H23: =Model!P43 -> 20210.336
B24: Long Term Liabilities values increased by 2% | C24: =Model!K49 -> 1061.9322 | D24: =Model!L49 -> 1093.7902 | E24: =Model!M49 -> 1126.6039 | F24: =Model!N49 -> 1160.402 | G24: =Model!O49 -> 1195.214 | H24: =Model!P49 -> 1231.0705
B25: Long Term Assets increased by 5% | C25: =Model!K67 -> 13251.878 | D25: =Model!L67 -> 11169.811 | E25: =Model!M67 -> 9447.3265 | F25: =Model!N67 -> 8018.1912 | G25: =Model!O67 -> 6828.8499 | H25: =Model!P67 -> 5835.9472
B26: Cash & Bank Balances increased by 5% | C26: =Model!K84 -> 639.3765 | D26: =Model!L84 -> 671.34533 | E26: =Model!M84 -> 704.91259 | F26: =Model!N84 -> 740.15822 | G26: =Model!O84 -> 777.16613 | H26: =Model!P84 -> 816.02444

Sheet Q1
D2: 1. Company & Industry Overview Brief on Hero MotoCorp Hero MotoCorp is the largest two-wheeler manufacturer in India based in India, which was formerly a joint venture of Hero Cycles and the Honda Motor Company of Japan. The alliance was terminated in 2011 after Honda disposed of its 26% share to the Munjal family and the company changed its name to Hero MotoCorp in July 2011. Market Position: Hero MotoCorp company has one of the largest shares in India two-wheeler market standing at about 30% and continues to be the dominant motorcycle manufacturer in India. Key Products: Hero Splendor and Hero HF Deluxe are the best sellers which have contributed 40% of all sales. Karizma XMR, H-D X440 (Harley-Davidson cooperation) and MAVRICK 440 belong to the premium segment with the contribution of about 25% of revenue. Xtreme and Maestro series are also in the company. Revenue Sources: Hero MotoCorp has made a revenue of INR 37,455.72 Crores in the year 2024. The Indian domestic market has contributed 95% of the total revenues, motorcycles being the main business and expanding the export to Africa and Latin America. Industry Trends & Market Dynamics In 2024-25, the market of the two-wheeler in India hit 19.6 million units, with a growth rate of 9.1% per year. By 2025, the market size is projected to be 31.59 billion with a growth of 2.4% CAGR and by 2030 will be 34.74 billion. Competitive Landscape: The industry is relatively concentrated as the five leading companies have a market share of 87.94%. Hero MotoCorp had a market share of 35% in November 2024 followed by Honda with 25%, TVS with 16%, and Bajaj with 11.63%. Honda has gained a lot in FY25, and its share has grown to 25.37% compared to 23.36%, whereas Hero has gone down to 28.84% from 30.79%. Growth Drivers: Electric cars are on spectacular expansion with an estimated growth rate of 21% in the period of 2024 to 2029. Electric two-wheelers had a market of 960,000 units in 2024, and is projected to expand at a CAGR of 28.5% to 11.1 million units by 2033. Regulatory Trends: Starting April 1, 2020, BS6 emission norms became mandatory, as they were obliged to have onboard diagnostics and stricter control of pollution. BS6 fuel has 5 times lower sulphur concentration and NOx is less by 70% in diesel and 25 percent in petrol engines.
