Workbook

Sheet Section A
E1: Cash Flow Analysis
E2: Year | F2: 0 | G2: 1 | H2: 2 | I2: 3 | J2: 4
E3: Machinery Cost (Initial investment) | F3: 820000
E4: Working capital | F4: 40000
E5: Total Initial Investment | F5: =F3+F4 -> 860000
E6: Residual value of machine | F6: 80000
E7: Discount Rate | F7: 0.085
E8: Expected cash inflows (revenue) | G8: 310000 | H8: =G8*110% -> 341000 | I8: =H8*110% -> 375100 | J8: =I8*110% -> 412610
E9: Total Net Cash Inflows | G9: =G8 -> 310000 | H9: =H8 -> 341000 | I9: =I8 -> 375100 | J9: =J8+F6 -> 492610
E11: Payback Period
E12: Year | F12: Net Cash flow | G12: Cumulative cash flow
E13: ='Section A'!E34 -> 0 | F13: =-F5 -> -860000 | G13: =F13 -> -860000
E14: ='Section A'!E35 -> 1 | F14: =G9 -> 310000 | G14: =G13+F14 -> -550000
E15: ='Section A'!E36 -> 2 | F15: =H9 -> 341000 | G15: =G14+F15 -> -209000
E16: ='Section A'!E37 -> 3 | F16: =I9 -> 375100 | G16: =G15+F16 -> 166100
E17: ='Section A'!E38 -> 4 | F17: =J9 -> 492610 | G17: =G16+F17 -> 658710
E18: Payback Period | G18: =E15+(209000/F16) -> 2.5571848
E19: Converting to year and month | G19: 2 years 6 months
E21: =E30 -> Accounting Rate of Return (ARR)
E22: Particular | F22: Cash flow | G22: Depreciation | H22: Net Profit
E23: 1 | F23: ='Section A'!F35 -> 310000 | G23: =(F5-F6)/4 -> 195000 | H23: =F23-G23 -> 115000
E24: 2 | F24: ='Section A'!F36 -> 341000 | G24: =G23 -> 195000 | H24: =F24-G24 -> 146000
E25: 3 | F25: ='Section A'!F37 -> 375100 | G25: =G24 -> 195000 | H25: =F25-G25 -> 180100
E26: 4 | F26: ='Section A'!F38 -> 492610 | G26: =G25 -> 195000 | H26: =F26-G26 -> 297610
F27: Workings
E28: Net Average Profit | F28: (115000+146000+180100+297610)/4 | H28: =AVERAGE(H23:H26) -> 184677.5
E29: Average investment | F29: (820000+40000+80000) | H29: =(F3+F4+F6)/2 -> 470000
E30: Accounting Rate of Return (ARR) | F30: (184678/470000) | H30: =H28/H29 -> 0.39293085
E32: Net Present Value (NPV)
E33: Items | F33: =F42 -> Cash flow | G33: Discount Factor @ 8.5% | H33: =H42 -> Discounted cashflow
E34: 0 | F34: =-F5 -> -860000 | G34: =1/(1+8.5%)^E34 -> 1 | H34: =F34*G34 -> -860000
E35: 1 | F35: =G9 -> 310000 | G35: =1/(1+8.5%)^E35 -> 0.92165899 | H35: =F35*G35 -> 285714.29
E36: 2 | F36: =H9 -> 341000 | G36: =1/(1+8.5%)^E36 -> 0.84945529 | H36: =F36*G36 -> 289664.25
E37: 3 | F37: =I9 -> 375100 | G37: =1/(1+8.5%)^E37 -> 0.7829081 | H37: =F37*G37 -> 293668.83
E38: 4 | F38: =J9 -> 492610 | G38: =1/(1+8.5%)^E38 -> 0.72157428 | H38: =F38*G38 -> 355454.71
E39: NPV | H39: =SUM(H34:H38) -> 364502.07
E41: Negative present value of cash flow
E42: Items | F42: Cash flow | G42: Discounted factors | H42: Discounted cashflow
E43: Discount Rate | F43: 0.27
E44: 0 | F44: =F34 -> -860000 | G44: =1/(1+$F$43)^E44 -> 1 | H44: =F44*G44 -> -860000
E45: 1 | F45: =F35 -> 310000 | G45: =1/(1+$F$43)^E45 -> 0.78740157 | H45: =F45*G45 -> 244094.49
E46: 2 | F46: =F36 -> 341000 | G46: =1/(1+$F$43)^E46 -> 0.62000124 | H46: =F46*G46 -> 211420.42
E47: 3 | F47: =F37 -> 375100 | G47: =1/(1+$F$43)^E47 -> 0.48818995 | H47: =F47*G47 -> 183120.05
E48: 4 | F48: =F38 -> 492610 | G48: =1/(1+$F$43)^E48 -> 0.38440154 | H48: =F48*G48 -> 189360.04
E49: Negative present value of cash flow | H49: =SUM(H44:H48) -> -32004.996
H53: =8.5%+(H39/(H39-H49))*(20%-8.5%) -> 0.19071751

Sheet Section B
C2: 1. Forecasting the Quarterly Sales of Manufacturing
C3: Product A: Packaged Energy Bar
C4: Quarter | D4: Units Sold | E4: Selling price per unit | F4: Sales Revenue
C5: 1 | D5: 18000 | E5: 2 | F5: =D5*E5 -> 36000
C6: 2 | D6: 22000 | E6: 2 | F6: =D6*E6 -> 44000
C7: 3 | D7: 26000 | E7: 2 | F7: =D7*E7 -> 52000
C8: 4 | D8: 30000 | E8: 2 | F8: =D8*E8 -> 60000
C9: Total Value | D9: =SUM(D5:D8) -> 96000 | F9: =SUM(F5:F8) -> 192000
C10: Product B: Bottled Fruit Juice
C11: Quarter | D11: Units Sold | E11: Selling price per unit | F11: =F4 -> Sales Revenue
C12: 1 | D12: 12000 | E12: 3 | F12: =D12*E12 -> 36000
C13: 2 | D13: 15000 | E13: 3 | F13: =D13*E13 -> 45000
C14: 3 | D14: 18000 | E14: 3 | F14: =D14*E14 -> 54000
C15: 4 | D15: 22000 | E15: 3 | F15: =D15*E15 -> 66000
C16: Total Value | D16: =SUM(D12:D15) -> 67000 | F16: =SUM(F12:F15) -> 201000
C17: Total Forecasted Revenue for Year 1 | F17: =F9+F16 -> 393000
C19: 2. Variable Cost per Unit of Manufacturing
C20: =C3 -> Product A: Packaged Energy Bar
C21: Details | D21: Cost per Unit
C22: Oats and cereal base | D22: 0.35
C23: Sweeteners and binding agents | D23: 0.22
C24: Packaging materials | D24: 0.18
C25: Direct labour | D25: 0.3
C26: Total Variable Cost | D26: =SUM(D22:D25) -> 1.05
C27: =C10 -> Product B: Bottled Fruit Juice
C28: Details | D28: Cost per Unit
C29: Fresh fruit ingredients | D29: 0.9
C30: Bottles and caps | D30: 0.4
C31: Direct labour | D31: 0.45
C32: Utilities for processing | D32: 0.25
C33: Total Variable Cost | D33: =SUM(D29:D32) -> 2
C35: 3. Annual Fixed Costs of Manufacturing
C36: Fixed Cost | D36: Value
C37: Factory rent | D37: 40000
C38: Salaries of management and supervisors | D38: 70000
C39: Machinery depreciation | D39: 30000
C40: Insurance | D40: 12000
C41: Business licences and compliance fees | D41: 8000
C42: Marketing and advertising | D42: 12000
C43: Administration and office expenses | D43: 18000
C44: Security and maintenance contracts | D44: 14000
C45: Total Annual Fixed Costs | D45: =SUM(D37:D44) -> 204000
C47: 4. Break-even Analysis of Manufacturing - Marginal Costing
C48: Items | D48: =C3 -> Product A: Packaged Energy Bar | E48: =C10 -> Product B: Bottled Fruit Juice
C49: Total annual fixed costs per Product | D49: =$D$45*50% -> 102000 | E49: =$D$45*50% -> 102000
C50: Selling price per unit | D50: =E5 -> 2 | E50: =E12 -> 3
C51: Variable cost per unit | D51: =D26 -> 1.05 | E51: =D33 -> 2
C52: Contribution per unit | D52: =D50-D51 -> 0.95 | E52: =E50-E51 -> 1
C53: Break-even Units | D53: =D49/D52 -> 107368.42 | E53: =E49/E52 -> 102000
C54: Break-even Revenue | D54: =D53*D50 -> 214736.84 | E54: =E53*E50 -> 306000
C57: 5. Annual Margin of Safety of Manufacturing
C58: Details | D58: =D48 -> Product A: Packaged Energy Bar | E58: =E48 -> Product B: Bottled Fruit Juice
C59: Forecast annual sales unit | D59: =D9 -> 96000 | E59: =D16 -> 67000
C60: Break-even sales | D60: =D53 -> 107368.42 | E60: =E53 -> 102000
C61: Margin of Safety (Units) | D61: =D59-D60 -> -11368.421 | E61: =E59-E60 -> -35000
C62: Margin of Safety (%) | D62: =D61/D59 -> -0.11842105 | E62: =E61/E59 -> -0.52238806
C65: 6. Annual Marginal Costing Income Statement
C66: Particulars | D66: =D58 -> Product A: Packaged Energy Bar | E66: =E58 -> Product B: Bottled Fruit Juice
C67: Sales volume | D67: =D59 -> 96000 | E67: =E59 -> 67000
C68: Selling price | D68: =D50 -> 2 | E68: =E50 -> 3
C69: Variable cost per unit | D69: =D51 -> 1.05 | E69: =E51 -> 2
C70: Fixed costs allocated | D70: =D49 -> 102000 | E70: =E49 -> 102000
C71: Sales revenue | D71: =D67*D68 -> 192000 | E71: =E67*E68 -> 201000
C72: Less: Variable costs | D72: =D67*D69 -> 100800 | E72: =E67*E69 -> 134000
C73: Contribution | D73: =D71-D72 -> 91200 | E73: =E71-E72 -> 67000
C74: Operating profit | D74: =D73-D70 -> -10800 | E74: =E73-E70 -> -35000
C77: 8. Single Limiting Factor Analysis
C78: Particulars | D78: =D66 -> Product A: Packaged Energy Bar | E78: =E66 -> Product B: Bottled Fruit Juice
C79: Limiting Factor | D79: Direct labour time
C80: Labour Requirement per Unit | D80: 0.02 | E80: 0.05
C81: Contribution per Unit | D81: =D52 -> 0.95 | E81: =E52 -> 1
C82: Contribution per hour | D82: =D81/D80 -> 47.5 | E82: =E81/E80 -> 20
C83: New Optimal Production Mix
C84: Direct labour hours | D84: 120000
C85: =D78 -> Product A: Packaged Energy Bar
C86: Maximum Energy Bar Production (Units) | D86: =D84/E80 -> 2400000
C87: Labour used (hours) | D87: =E67*E80 -> 3350
C88: Remaining Labour Hours | D88: =D84-D87 -> 116650
C89: =E78 -> Product B: Bottled Fruit Juice
C90: Bottled Fruit Juice Production (Units) | D90: =D88/D80 -> 5832500
C91: Demand constraint limits Bottled Fruit Juice (Units) | D91: 60000
C92: Bottled Fruit Juice Labour used (hours) | D92: =D91*D80 -> 1200
C93: Unused Labour Capacity (hours) | D93: =D84-(D87+D92) -> 115450
C94: Maximum Contribution Achieved
C95: Product | D95: =D78 -> Product A: Packaged Energy Bar | E95: =E78 -> Product B: Bottled Fruit Juice
C96: Units | D96: =D9 -> 96000 | E96: =D16 -> 67000
C97: =C81 -> Contribution per Unit | D97: =D81 -> 0.95 | E97: =E81 -> 1
C98: Total Contribution on New Optimal Production Mix | D98: =D96*D97 -> 91200 | E98: =E96*E97 -> 67000
